ritm_annotation/.gitignore
ritm_annotation/VERSION
ritm_annotation/__init__.py
ritm_annotation/__main__.py
ritm_annotation/base.py
ritm_annotation/__pycache__/__init__.cpython-312.pyc
ritm_annotation/__pycache__/base.cpython-312.pyc
ritm_annotation/cli/README.md
ritm_annotation/cli/__init__.py
ritm_annotation/cli/annotate/__init__.py
ritm_annotation/cli/annotate/annotator.py
ritm_annotation/cli/annotate/canvas.py
ritm_annotation/cli/annotate/controller.py
ritm_annotation/cli/annotate/wrappers.py
ritm_annotation/cli/convert_to_coco/__init__.py
ritm_annotation/cli/dataset_lint/__init__.py
ritm_annotation/cli/finetune/__init__.py
ritm_annotation/cli/finetune/dataset.py
ritm_annotation/cli/finetune/finetune.py
ritm_annotation/cli/model_info/__init__.py
ritm_annotation/cli/model_info/model_info.py
ritm_annotation/cli/train/__init__.py
ritm_annotation/cli/train/train.py
ritm_annotation/data/__init__.py
ritm_annotation/data/base.py
ritm_annotation/data/compose.py
ritm_annotation/data/points_sampler.py
ritm_annotation/data/sample.py
ritm_annotation/data/transforms.py
ritm_annotation/data/__pycache__/__init__.cpython-312.pyc
ritm_annotation/data/__pycache__/base.cpython-312.pyc
ritm_annotation/data/__pycache__/compose.cpython-312.pyc
ritm_annotation/data/__pycache__/points_sampler.cpython-312.pyc
ritm_annotation/data/__pycache__/sample.cpython-312.pyc
ritm_annotation/data/__pycache__/transforms.cpython-312.pyc
ritm_annotation/data/datasets/__init__.py
ritm_annotation/data/datasets/ade20k.py
ritm_annotation/data/datasets/berkeley.py
ritm_annotation/data/datasets/coco.py
ritm_annotation/data/datasets/coco_lvis.py
ritm_annotation/data/datasets/davis.py
ritm_annotation/data/datasets/grabcut.py
ritm_annotation/data/datasets/images_dir.py
ritm_annotation/data/datasets/lvis.py
ritm_annotation/data/datasets/openimages.py
ritm_annotation/data/datasets/pascalvoc.py
ritm_annotation/data/datasets/sbd.py
ritm_annotation-0.12.2.dist-info/METADATA
ritm_annotation-0.12.2.dist-info/WHEEL
ritm_annotation-0.12.2.dist-info/entry_points.txt
ritm_annotation-0.12.2.dist-info/top_level.txt
ritm_annotation-0.12.2.dist-info/RECORD
ritm_annotation-0.12.2.dist-info/licenses/LICENSE
