Metadata-Version: 2.1
Name: ritm_annotation
Version: 0.12.2
License-File: LICENSE
Requires-Dist: easydict
Requires-Dist: pillow
Requires-Dist: scipy
Requires-Dist: tensorboard
Requires-Dist: torchvision
Requires-Dist: opencv-python-headless
Requires-Dist: numpy
Requires-Dist: tqdm
Requires-Dist: pycocotools
Requires-Dist: albumentations ==1.3.1
Provides-Extra: dev
Requires-Dist: pytest ; extra == 'dev'
Requires-Dist: pytest-cov ; extra == 'dev'
Requires-Dist: coverage ; extra == 'dev'
Requires-Dist: ruff ; extra == 'dev'
Requires-Dist: mypy ; extra == 'dev'
Requires-Dist: gitchangelog ; extra == 'dev'
Requires-Dist: mkdocs ; extra == 'dev'
Requires-Dist: mkdocstrings ; extra == 'dev'
